ceserver_api/__init__.py
ceserver_api/client.py
ceserver_api/commands.py
ceserver_api/data_classes.py
ceserver_api/port_help.py
ceserver_api/structs.py
ceserver_api-0.1.2.dist-info/licenses/LICENSE
ceserver_api-0.1.2.dist-info/METADATA
ceserver_api-0.1.2.dist-info/WHEEL
ceserver_api-0.1.2.dist-info/top_level.txt
ceserver_api-0.1.2.dist-info/RECORD
