Metadata-Version: 2.4
Name: ceserver-api
Version: 0.1.2
Summary: Python Client to comunicate with Cheat Engine's ceserver
Author-email: Felipe Gatica <felipeparagati@gmail.com>
License: BSD
Project-URL: Homepage, https://github.com/juzt3/ceserver-api
Project-URL: Repository, https://github.com/juzt3/ceserver-api
Project-URL: Issues, https://github.com/juzt3/ceserver-api/issues
Classifier: Programming Language :: Python :: 3
Classifier: Operating System :: OS Independent
Requires-Python: >=3.8
License-File: LICENSE
Requires-Dist: construct>=2.10
Dynamic: license-file
